nft/__init__.py
nft/image.py
nft_toolkit-0.1.1.dist-info/LICENSE
nft_toolkit-0.1.1.dist-info/METADATA
nft_toolkit-0.1.1.dist-info/WHEEL
nft_toolkit-0.1.1.dist-info/top_level.txt
nft_toolkit-0.1.1.dist-info/RECORD
