Metadata-Version: 2.1
Name: nft-toolkit
Version: 0.1.1
Summary: A tool to generate a randomized 2D-image         NFT collection based on nft attribute layers
Home-page: https://github.com/nanolaboratory/nft-toolkit
Author: Nano Labs LLC
Author-email: hello@nanolabs.dev
License: UNKNOWN
Project-URL: Bug Tracker, https://github.com/nanolaboratory/nft-toolkit/issues
Platform: UNKNOWN
Classifier: Programming Language :: Python :: 3
Classifier: License :: OSI Approved :: MIT License
Classifier: Operating System :: OS Independent
Requires-Python: >=3.6
License-File: LICENSE
Requires-Dist: Pillow (==8.3.2)
Requires-Dist: simplejson
